MANIFEST.in
README.rst
setup.py
dataclean/__init__.py
dataclean/cleaning.py
dataclean/codegen.py
dataclean/manager.py
dataclean/pipeline.py
dataclean/widget.py
dataclean/static/iosbadge.js
dataclean/static/jquery.tablesorter.min.js
dataclean/static/main.css
dataclean/static/main.js
sherlockml_dataclean.egg-info/PKG-INFO
sherlockml_dataclean.egg-info/SOURCES.txt
sherlockml_dataclean.egg-info/dependency_links.txt
sherlockml_dataclean.egg-info/requires.txt
sherlockml_dataclean.egg-info/top_level.txt