Metadata-Version: 1.0
Name: sherlockml-dataclean
Version: 0.2.2
Summary: Interactive cleaning for pandas DataFrames
Home-page: https://sherlockml.com
Author: ASI Data Science
Author-email: engineering@asidatascience.com
License: Apache 2.0
Platform: UNKNOWN
